foo_project/__init__.py
foo_project/main.py
FlavorDM-0.0.2.dist-info/METADATA
FlavorDM-0.0.2.dist-info/WHEEL
FlavorDM-0.0.2.dist-info/top_level.txt
FlavorDM-0.0.2.dist-info/RECORD
